{
  "cli": {
    "version": ">= 16.0.0",
    "appVersionSource": "remote"
  },
  "build": {
    "development": {
      "developmentClient": true,
      "distribution": "internal",
      "android": {
        "buildType": "apk"
      }
    },
    "preview": {
      "distribution": "internal",
      "android": {
        "buildType": "apk"
      },
      "env": {
        "EXPO_PUBLIC_PAYHUB_BASE_URL": "https://staging.centyhq.com"
      }
    },
    "production": {
      "android": {
        "buildType": "app-bundle"
      }
    }
  },
  "submit": {
    "production": {}
  }
}
